dirdict.py
dirdict-1.1.1.dist-info/LICENSE
dirdict-1.1.1.dist-info/WHEEL
dirdict-1.1.1.dist-info/METADATA
dirdict-1.1.1.dist-info/RECORD
